junotorch/__init__.py
junotorch/vision/__init__.py
junotorch-0.4.5.dist-info/METADATA
junotorch-0.4.5.dist-info/WHEEL
junotorch-0.4.5.dist-info/top_level.txt
junotorch-0.4.5.dist-info/RECORD
