Metadata-Version: 2.1
Name: junotorch
Version: 0.4.5
Summary: Custom pytorch modules that I use often
Home-page: https://github.com/juno-hwang/junotorch
Author: Juno Hwang
Author-email: wnsdh10@snu.ac.kr
License: UNKNOWN
Platform: UNKNOWN
Classifier: Programming Language :: Python :: 3
Classifier: License :: OSI Approved :: MIT License
Classifier: Operating System :: OS Independent
Requires-Python: >=3.6
Requires-Dist: numpy
Requires-Dist: matplotlib
Requires-Dist: torch
